nr_documents_records/__init__.py
nr_documents_records/config.py
nr_documents_records/ext.py
nr_documents_records/proxies.py
nr_documents_records/version.py
nr_documents_records/views.py
nr_documents_records/records/__init__.py
nr_documents_records/records/api.py
nr_documents_records/records/dumper.py
nr_documents_records/records/models.py
nr_documents_records/records/multilingual_dumper.py
nr_documents_records/records/jsonschemas/__init__.py
nr_documents_records/records/jsonschemas/nr-documents-records-1.0.0.json
nr_documents_records/records/mappings/__init__.py
nr_documents_records/records/mappings/v7/__init__.py
nr_documents_records/records/mappings/v7/nr_documents_records/__init__.py
nr_documents_records/records/mappings/v7/nr_documents_records/nr-documents-records-1.0.0.json
nr_documents_records/resources/__init__.py
nr_documents_records/resources/config.py
nr_documents_records/resources/resource.py
nr_documents_records/services/__init__.py
nr_documents_records/services/config.py
nr_documents_records/services/facets.py
nr_documents_records/services/i18nStr_schema.py
nr_documents_records/services/multilingual_schema.py
nr_documents_records/services/permissions.py
nr_documents_records/services/schema.py
nr_documents_records/services/search.py
nr_documents_records/services/service.py
nr_documents_records-1.0.0.dist-info/METADATA
nr_documents_records-1.0.0.dist-info/WHEEL
nr_documents_records-1.0.0.dist-info/entry_points.txt
nr_documents_records-1.0.0.dist-info/top_level.txt
nr_documents_records-1.0.0.dist-info/RECORD
