Metadata-Version: 2.1
Name: nr-documents-records
Version: 1.0.0
Summary: NR documents data model
Home-page: https://github.com/NarodniRepozitar/nr-documents-records
Author: CESNET
Author-email: bauer@cesnet.cz
License: MIT
Keywords: National Repository documents data model Invenio
Platform: any
Classifier: Development Status :: 5 - Production/Stable
Provides-Extra: tests
Requires-Dist: pytest (>=5.0.0) ; extra == 'tests'
Requires-Dist: pytest-cov (>=2.10.1) ; extra == 'tests'
Requires-Dist: pytest-runner (>=5.3.0) ; extra == 'tests'
Requires-Dist: oarepo-model-builder (>=0.9.24) ; extra == 'tests'
